LICENSE
MANIFEST.in
README.md
setup.cfg
setup.py
django_simple_cache_admin.egg-info/PKG-INFO
django_simple_cache_admin.egg-info/SOURCES.txt
django_simple_cache_admin.egg-info/dependency_links.txt
django_simple_cache_admin.egg-info/requires.txt
django_simple_cache_admin.egg-info/top_level.txt
simple_cache_admin/__init__.py
simple_cache_admin/admin.py
simple_cache_admin/models.py
simple_cache_admin/views.py
simple_cache_admin/templates/simple_cache_admin/index.html