Metadata-Version: 1.1
Name: django-simple-cache-admin
Version: 0.1.2
Summary: Cache administration tools for Django.
Home-page: https://github.com/7kfpun/django-simple-cache-admin
Author: kf
Author-email: 7kfpun@gmail.com
License: MIT
Platform: UNKNOWN
Classifier: Development Status :: 4 - Beta
Classifier: Environment :: Web Environment
Classifier: Framework :: Django
Classifier: Intended Audience :: Developers
Classifier: Intended Audience :: System Administrators
Classifier: License :: OSI Approved :: MIT License
Classifier: Operating System :: OS Independent
Classifier: Programming Language :: Python :: 2
Classifier: Programming Language :: Python :: 3
Classifier: Topic :: Internet :: WWW/HTTP :: Site Management
